inapp_purchases/__init__.py
inapp_purchases/app_store.py
inapp_purchases/google_play.py
inapp_purchases/inapp_service.py
inapp_purchases/response.py
inapp_purchases/subscription_status.py
inapp_purchases-0.4.2.dist-info/DESCRIPTION.rst
inapp_purchases-0.4.2.dist-info/METADATA
inapp_purchases-0.4.2.dist-info/RECORD
inapp_purchases-0.4.2.dist-info/WHEEL
inapp_purchases-0.4.2.dist-info/metadata.json
inapp_purchases-0.4.2.dist-info/top_level.txt
